ascvd_calculator/__init__.py
emji_ascvd_calculator-0.1.0.dist-info/LICENSE
emji_ascvd_calculator-0.1.0.dist-info/METADATA
emji_ascvd_calculator-0.1.0.dist-info/WHEEL
emji_ascvd_calculator-0.1.0.dist-info/top_level.txt
emji_ascvd_calculator-0.1.0.dist-info/RECORD
