Metadata-Version: 2.1
Name: emji-ascvd-calculator
Version: 0.1.0
Summary: ASCVD risk calculator based on user input parameters
Home-page: https://github.com/emji555/ascvd_calculator
Author: Eslam Mohamed Jaber Elmasry
Author-email: emji555@gmail.com
License: UNKNOWN
Platform: UNKNOWN
Classifier: Programming Language :: Python :: 3
Classifier: License :: OSI Approved :: MIT License
Classifier: Operating System :: OS Independent
Requires-Python: >=3.6
